.gitignore
MANIFEST.in
README.rst
setup.cfg
setup.py
docs/HISTORY.txt
docs/LICENSE.GPL
docs/LICENSE.txt
docs/MANUAL.txt
raptus/__init__.py
raptus.article.allcontent.egg-info/PKG-INFO
raptus.article.allcontent.egg-info/SOURCES.txt
raptus.article.allcontent.egg-info/dependency_links.txt
raptus.article.allcontent.egg-info/entry_points.txt
raptus.article.allcontent.egg-info/namespace_packages.txt
raptus.article.allcontent.egg-info/not-zip-safe
raptus.article.allcontent.egg-info/requires.txt
raptus.article.allcontent.egg-info/top_level.txt
raptus/article/__init__.py
raptus/article/allcontent/__init__.py
raptus/article/allcontent/configure.zcml
raptus/article/allcontent/extender.py
raptus/article/allcontent/interfaces.py
raptus/article/allcontent/vocabulary.py
raptus/article/allcontent/browser/__init__.py
raptus/article/allcontent/browser/allcontent.gif
raptus/article/allcontent/browser/allcontent.pt
raptus/article/allcontent/browser/allcontent.py
raptus/article/allcontent/browser/allcontent_view.pt
raptus/article/allcontent/browser/configure.zcml
raptus/article/allcontent/browser/empty.py
raptus/article/allcontent/i18n/raptus.article-de.mo
raptus/article/allcontent/i18n/raptus.article-de.po
raptus/article/allcontent/i18n/raptus.article.pot
raptus/article/allcontent/profiles/default/cssregistry.xml
raptus/article/allcontent/profiles/default/metadata.xml
raptus/article/allcontent/profiles/default/skins.xml
raptus/article/allcontent/profiles/default/viewlets.xml
raptus/article/allcontent/skins/raptus_article_allcontent/raptus.article.allcontent.css.dtml