Metadata-Version: 1.1
Name: raptus.article.allcontent
Version: 1.0a3
Summary: Provides a component which displays the whole content of the contained articles
Home-page: https://github.com/Raptus/raptus.article.allcontent
Author: Raptus AG
Author-email: dev@raptus.com
License: GPL
Platform: UNKNOWN
Classifier: Programming Language :: Python
Classifier: Topic :: Software Development :: Libraries :: Python Modules
